unicodedata_reader/__init__.py
unicodedata_reader/__main__.py
unicodedata_reader/bidi_brackets.py
unicodedata_reader/cli.py
unicodedata_reader/compressor.py
unicodedata_reader/east_asian_width.py
unicodedata_reader/emoji.py
unicodedata_reader/entry.py
unicodedata_reader/general_category.py
unicodedata_reader/line_break.py
unicodedata_reader/reader.py
unicodedata_reader/set.py
unicodedata_reader/vertical_orientation.py
unicodedata_reader-1.3.7.dist-info/METADATA
unicodedata_reader-1.3.7.dist-info/WHEEL
unicodedata_reader-1.3.7.dist-info/entry_points.txt
unicodedata_reader-1.3.7.dist-info/licenses/LICENSE
unicodedata_reader-1.3.7.dist-info/RECORD
