Metadata-Version: 2.4
Name: unicodedata-reader
Version: 1.3.7
Project-URL: repository, https://github.com/kojiishi/unicodedata-reader
Author-email: Koji Ishii <kojii@chromium.org>
License-Expression: Apache-2.0
License-File: LICENSE
Requires-Python: >=3.9
Requires-Dist: platformdirs>=4.3.8
